[{"total_thrust": 7253.6669957030235, "a0.kdz": 20, "ith_runtime": 16.075680017471313, "setpoint": [1, 1, 2], "z_crossings": 1, "y_crossings": 1, "x_crossings": 1, "z_over_shoot": 0.0065344939290259418, "a0.kpx": 5, "a0.kpy": 5, "a0.kpz": 40, "return_val2": 1, "a0.kdx": 10, "a0.kdy": 10, "a0.kiy": 0.40000000000000002, "a0.kix": 0.40000000000000002, "x_over_shoot": 0.026399423919776011, "y_over_shoot": 0.02722912325895166, "a0.ending_iteration": 501, "a0.kiz": 15}, {"ith_runtime": 25.130042791366577, "setpoint": [1, 1, 2], "a0.kpx": 5, "a0.kpy": 5, "a0.kpz": 40, "a0.kiz": 20, "a0.kiy": 0.40000000000000002, "a0.kix": 0.40000000000000002, "a0.ending_iteration": 999, "return_val2": null, "a0.kdx": 10, "a0.kdy": 10, "a0.kdz": 20}, {"ith_runtime": 24.692668914794922, "setpoint": [1, 1, 2], "a0.kpx": 5, "a0.kpy": 5, "a0.kpz": 40, "a0.kiz": 25, "a0.kiy": 0.40000000000000002, "a0.kix": 0.40000000000000002, "a0.ending_iteration": 999, "return_val2": null, "a0.kdx": 10, "a0.kdy": 10, "a0.kdz": 20}, {"total_thrust": 7268.7274187209778, "a0.kdz": 20, "ith_runtime": 15.631160974502563, "setpoint": [1, 1, 2], "z_crossings": 1, "y_crossings": 1, "x_crossings": 1, "z_over_shoot": 0.23911610856474308, "a0.kpx": 5, "a0.kpy": 5, "a0.kpz": 40, "return_val2": 1, "a0.kdx": 10, "a0.kdy": 10, "a0.kiy": 0.40000000000000002, "a0.kix": 0.40000000000000002, "x_over_shoot": 0.027775044488512979, "y_over_shoot": 0.028162618945356321, "a0.ending_iteration": 503, "a0.kiz": 30}, {"total_thrust": 7248.8029441136678, "a0.kdz": 20, "ith_runtime": 15.500710010528564, "setpoint": [1, 1, 2], "z_crossings": 2, "y_crossings": 1, "x_crossings": 1, "z_over_shoot": 0.31378008145417935, "a0.kpx": 5, "a0.kpy": 5, "a0.kpz": 40, "return_val2": 1, "a0.kdx": 10, "a0.kdy": 10, "a0.kiy": 0.40000000000000002, "a0.kix": 0.40000000000000002, "x_over_shoot": 0.026746341755484293, "y_over_shoot": 0.027046386766855113, "a0.ending_iteration": 501, "a0.kiz": 35}, {"ith_runtime": 24.083060026168823, "setpoint": [1, 1, 2], "a0.kpx": 5, "a0.kpy": 5, "a0.kpz": 40, "a0.kiz": 40, "a0.kiy": 0.40000000000000002, "a0.kix": 0.40000000000000002, "a0.ending_iteration": 999, "return_val2": null, "a0.kdx": 10, "a0.kdy": 10, "a0.kdz": 20}]