[{"ith_runtime": 17.53167700767517, "setpoint": [1, 1, 2], "a0.kpx": 25, "a0.kpy": 25, "a0.kpz": 30, "a0.kiz": 15, "a0.kiy": 0.80000000000000004, "a0.kix": 0.80000000000000004, "a0.ending_iteration": 999, "return_val2": null, "a0.kdx": 5, "a0.kdy": 5, "a0.kdz": 20}, {"ith_runtime": 14.121397972106934, "setpoint": [1, 1, 2], "a0.kpx": 25, "a0.kpy": 25, "a0.kpz": 30, "a0.kiz": 20, "a0.kiy": 0.80000000000000004, "a0.kix": 0.80000000000000004, "a0.ending_iteration": 999, "return_val2": null, "a0.kdx": 5, "a0.kdy": 5, "a0.kdz": 20}, {"ith_runtime": 16.849979877471924, "setpoint": [1, 1, 2], "a0.kpx": 25, "a0.kpy": 25, "a0.kpz": 30, "a0.kiz": 25, "a0.kiy": 0.80000000000000004, "a0.kix": 0.80000000000000004, "a0.ending_iteration": 999, "return_val2": null, "a0.kdx": 5, "a0.kdy": 5, "a0.kdz": 20}, {"ith_runtime": 14.679133176803589, "setpoint": [1, 1, 2], "a0.kpx": 25, "a0.kpy": 25, "a0.kpz": 30, "a0.kiz": 30, "a0.kiy": 0.80000000000000004, "a0.kix": 0.80000000000000004, "a0.ending_iteration": 999, "return_val2": null, "a0.kdx": 5, "a0.kdy": 5, "a0.kdz": 20}, {"ith_runtime": 18.58320713043213, "setpoint": [1, 1, 2], "a0.kpx": 25, "a0.kpy": 25, "a0.kpz": 30, "a0.kiz": 35, "a0.kiy": 0.80000000000000004, "a0.kix": 0.80000000000000004, "a0.ending_iteration": 999, "return_val2": null, "a0.kdx": 5, "a0.kdy": 5, "a0.kdz": 20}, {"ith_runtime": 19.5577609539032, "setpoint": [1, 1, 2], "a0.kpx": 25, "a0.kpy": 25, "a0.kpz": 30, "a0.kiz": 40, "a0.kiy": 0.80000000000000004, "a0.kix": 0.80000000000000004, "a0.ending_iteration": 999, "return_val2": null, "a0.kdx": 5, "a0.kdy": 5, "a0.kdz": 20}]