[{"ith_runtime": 18.73861789703369, "setpoint": [1, 1, 2], "a0.kpx": 25, "a0.kpy": 25, "a0.kpz": 30, "a0.kiz": 15, "a0.kiy": 0.80000000000000004, "a0.kix": 0.80000000000000004, "a0.ending_iteration": 999, "return_val2": null, "a0.kdx": 10, "a0.kdy": 10, "a0.kdz": 50}, {"ith_runtime": 20.824355125427246, "setpoint": [1, 1, 2], "a0.kpx": 25, "a0.kpy": 25, "a0.kpz": 30, "a0.kiz": 20, "a0.kiy": 0.80000000000000004, "a0.kix": 0.80000000000000004, "a0.ending_iteration": 999, "return_val2": null, "a0.kdx": 10, "a0.kdy": 10, "a0.kdz": 50}, {"ith_runtime": 23.83854913711548, "setpoint": [1, 1, 2], "a0.kpx": 25, "a0.kpy": 25, "a0.kpz": 30, "a0.kiz": 25, "a0.kiy": 0.80000000000000004, "a0.kix": 0.80000000000000004, "a0.ending_iteration": 999, "return_val2": null, "a0.kdx": 10, "a0.kdy": 10, "a0.kdz": 50}, {"ith_runtime": 19.65071702003479, "setpoint": [1, 1, 2], "a0.kpx": 25, "a0.kpy": 25, "a0.kpz": 30, "a0.kiz": 30, "a0.kiy": 0.80000000000000004, "a0.kix": 0.80000000000000004, "a0.ending_iteration": 999, "return_val2": null, "a0.kdx": 10, "a0.kdy": 10, "a0.kdz": 50}, {"ith_runtime": 18.027558088302612, "setpoint": [1, 1, 2], "a0.kpx": 25, "a0.kpy": 25, "a0.kpz": 30, "a0.kiz": 35, "a0.kiy": 0.80000000000000004, "a0.kix": 0.80000000000000004, "a0.ending_iteration": 999, "return_val2": null, "a0.kdx": 10, "a0.kdy": 10, "a0.kdz": 50}, {"ith_runtime": 20.315644025802612, "setpoint": [1, 1, 2], "a0.kpx": 25, "a0.kpy": 25, "a0.kpz": 30, "a0.kiz": 40, "a0.kiy": 0.80000000000000004, "a0.kix": 0.80000000000000004, "a0.ending_iteration": 999, "return_val2": null, "a0.kdx": 10, "a0.kdy": 10, "a0.kdz": 50}]