[{"ith_runtime": 23.31451106071472, "setpoint": [1, 1, 2], "a0.kpx": 20, "a0.kpy": 20, "a0.kpz": 20, "a0.kiz": 15, "a0.kiy": 0.20000000000000001, "a0.kix": 0.20000000000000001, "a0.ending_iteration": 999, "return_val2": null, "a0.kdx": 20, "a0.kdy": 20, "a0.kdz": 20}, {"total_thrust": 7673.4140543579097, "a0.kdz": 20, "ith_runtime": 16.53093194961548, "setpoint": [1, 1, 2], "z_crossings": 2, "y_crossings": 1, "x_crossings": 1, "z_over_shoot": 0.22495076985718532, "a0.kpx": 20, "a0.kpy": 20, "a0.kpz": 20, "return_val2": 1, "a0.kdx": 20, "a0.kdy": 20, "a0.kiy": 0.20000000000000001, "a0.kix": 0.20000000000000001, "x_over_shoot": 0.0070143256332784176, "y_over_shoot": 0.0066671400654243484, "a0.ending_iteration": 539, "a0.kiz": 20}, {"total_thrust": 6942.9557834476036, "a0.kdz": 20, "ith_runtime": 14.74019193649292, "setpoint": [1, 1, 2], "z_crossings": 2, "y_crossings": 1, "x_crossings": 1, "z_over_shoot": 0.31314841679859695, "a0.kpx": 20, "a0.kpy": 20, "a0.kpz": 20, "return_val2": 1, "a0.kdx": 20, "a0.kdy": 20, "a0.kiy": 0.20000000000000001, "a0.kix": 0.20000000000000001, "x_over_shoot": 0.0022046925935725881, "y_over_shoot": 0.0017111091707944226, "a0.ending_iteration": 465, "a0.kiz": 25}, {"ith_runtime": 23.22793698310852, "setpoint": [1, 1, 2], "a0.kpx": 20, "a0.kpy": 20, "a0.kpz": 20, "a0.kiz": 30, "a0.kiy": 0.20000000000000001, "a0.kix": 0.20000000000000001, "a0.ending_iteration": 999, "return_val2": null, "a0.kdx": 20, "a0.kdy": 20, "a0.kdz": 20}, {"ith_runtime": 22.993822813034058, "setpoint": [1, 1, 2], "a0.kpx": 20, "a0.kpy": 20, "a0.kpz": 20, "a0.kiz": 35, "a0.kiy": 0.20000000000000001, "a0.kix": 0.20000000000000001, "a0.ending_iteration": 999, "return_val2": null, "a0.kdx": 20, "a0.kdy": 20, "a0.kdz": 20}, {"total_thrust": 8070.9329025346178, "a0.kdz": 20, "ith_runtime": 17.221835136413574, "setpoint": [1, 1, 2], "z_crossings": 3, "y_crossings": 1, "x_crossings": 1, "z_over_shoot": 0.5661908599536627, "a0.kpx": 20, "a0.kpy": 20, "a0.kpz": 20, "return_val2": 1, "a0.kdx": 20, "a0.kdy": 20, "a0.kiy": 0.20000000000000001, "a0.kix": 0.20000000000000001, "x_over_shoot": 0.0087574510476793321, "y_over_shoot": 0.0082548140649292279, "a0.ending_iteration": 579, "a0.kiz": 40}]