[{"ith_runtime": 15.782502889633179, "setpoint": [1, 1, 2], "a0.kpx": 5, "a0.kpy": 5, "a0.kpz": 30, "a0.kiz": 15, "a0.kiy": 0.40000000000000002, "a0.kix": 0.40000000000000002, "a0.ending_iteration": 999, "return_val2": null, "a0.kdx": 10, "a0.kdy": 10, "a0.kdz": 20}, {"ith_runtime": 16.17520499229431, "setpoint": [1, 1, 2], "a0.kpx": 5, "a0.kpy": 5, "a0.kpz": 30, "a0.kiz": 20, "a0.kiy": 0.40000000000000002, "a0.kix": 0.40000000000000002, "a0.ending_iteration": 999, "return_val2": null, "a0.kdx": 10, "a0.kdy": 10, "a0.kdz": 20}, {"total_thrust": 7250.9769284054755, "a0.kdz": 20, "ith_runtime": 7.996412038803101, "setpoint": [1, 1, 2], "z_crossings": 2, "y_crossings": 1, "x_crossings": 1, "z_over_shoot": 0.21710982330889994, "a0.kpx": 5, "a0.kpy": 5, "a0.kpz": 30, "return_val2": 1, "a0.kdx": 10, "a0.kdy": 10, "a0.kiy": 0.40000000000000002, "a0.kix": 0.40000000000000002, "x_over_shoot": 0.026536497903502987, "y_over_shoot": 0.027185474519895614, "a0.ending_iteration": 501, "a0.kiz": 25}, {"ith_runtime": 11.402065992355347, "setpoint": [1, 1, 2], "a0.kpx": 5, "a0.kpy": 5, "a0.kpz": 30, "a0.kiz": 30, "a0.kiy": 0.40000000000000002, "a0.kix": 0.40000000000000002, "a0.ending_iteration": 999, "return_val2": null, "a0.kdx": 10, "a0.kdy": 10, "a0.kdz": 20}, {"ith_runtime": 13.43297004699707, "setpoint": [1, 1, 2], "a0.kpx": 5, "a0.kpy": 5, "a0.kpz": 30, "a0.kiz": 35, "a0.kiy": 0.40000000000000002, "a0.kix": 0.40000000000000002, "a0.ending_iteration": 999, "return_val2": null, "a0.kdx": 10, "a0.kdy": 10, "a0.kdz": 20}, {"ith_runtime": 16.127660989761353, "setpoint": [1, 1, 2], "a0.kpx": 5, "a0.kpy": 5, "a0.kpz": 30, "a0.kiz": 40, "a0.kiy": 0.40000000000000002, "a0.kix": 0.40000000000000002, "a0.ending_iteration": 999, "return_val2": null, "a0.kdx": 10, "a0.kdy": 10, "a0.kdz": 20}]