[{"ith_runtime": 4.359502077102661, "setpoint": [1, 1, 2], "a0.kpx": 25, "a0.kpy": 25, "a0.kpz": 40, "a0.kiz": 15, "a0.kiy": 0.20000000000000001, "a0.kix": 0.20000000000000001, "a0.ending_iteration": 999, "return_val2": null, "a0.kdx": 5, "a0.kdy": 5, "a0.kdz": 40}, {"ith_runtime": 4.224837064743042, "setpoint": [1, 1, 2], "a0.kpx": 25, "a0.kpy": 25, "a0.kpz": 40, "a0.kiz": 20, "a0.kiy": 0.20000000000000001, "a0.kix": 0.20000000000000001, "a0.ending_iteration": 999, "return_val2": null, "a0.kdx": 5, "a0.kdy": 5, "a0.kdz": 40}, {"ith_runtime": 4.013013124465942, "setpoint": [1, 1, 2], "a0.kpx": 25, "a0.kpy": 25, "a0.kpz": 40, "a0.kiz": 25, "a0.kiy": 0.20000000000000001, "a0.kix": 0.20000000000000001, "a0.ending_iteration": 999, "return_val2": null, "a0.kdx": 5, "a0.kdy": 5, "a0.kdz": 40}, {"ith_runtime": 4.663504123687744, "setpoint": [1, 1, 2], "a0.kpx": 25, "a0.kpy": 25, "a0.kpz": 40, "a0.kiz": 30, "a0.kiy": 0.20000000000000001, "a0.kix": 0.20000000000000001, "a0.ending_iteration": 999, "return_val2": null, "a0.kdx": 5, "a0.kdy": 5, "a0.kdz": 40}, {"ith_runtime": 4.842141151428223, "setpoint": [1, 1, 2], "a0.kpx": 25, "a0.kpy": 25, "a0.kpz": 40, "a0.kiz": 35, "a0.kiy": 0.20000000000000001, "a0.kix": 0.20000000000000001, "a0.ending_iteration": 999, "return_val2": null, "a0.kdx": 5, "a0.kdy": 5, "a0.kdz": 40}, {"ith_runtime": 5.316749095916748, "setpoint": [1, 1, 2], "a0.kpx": 25, "a0.kpy": 25, "a0.kpz": 40, "a0.kiz": 40, "a0.kiy": 0.20000000000000001, "a0.kix": 0.20000000000000001, "a0.ending_iteration": 999, "return_val2": null, "a0.kdx": 5, "a0.kdy": 5, "a0.kdz": 40}]