[{"ith_runtime": 26.910176038742065, "setpoint": [1, 1, 2], "a0.kpx": 20, "a0.kpy": 20, "a0.kpz": 20, "a0.kiz": 15, "a0.kiy": 0.40000000000000002, "a0.kix": 0.40000000000000002, "a0.ending_iteration": 999, "return_val2": null, "a0.kdx": 15, "a0.kdy": 15, "a0.kdz": 30}, {"ith_runtime": 26.374351024627686, "setpoint": [1, 1, 2], "a0.kpx": 20, "a0.kpy": 20, "a0.kpz": 20, "a0.kiz": 20, "a0.kiy": 0.40000000000000002, "a0.kix": 0.40000000000000002, "a0.ending_iteration": 999, "return_val2": null, "a0.kdx": 15, "a0.kdy": 15, "a0.kdz": 30}, {"ith_runtime": 26.59471893310547, "setpoint": [1, 1, 2], "a0.kpx": 20, "a0.kpy": 20, "a0.kpz": 20, "a0.kiz": 25, "a0.kiy": 0.40000000000000002, "a0.kix": 0.40000000000000002, "a0.ending_iteration": 999, "return_val2": null, "a0.kdx": 15, "a0.kdy": 15, "a0.kdz": 30}, {"ith_runtime": 24.134260177612305, "setpoint": [1, 1, 2], "a0.kpx": 20, "a0.kpy": 20, "a0.kpz": 20, "a0.kiz": 30, "a0.kiy": 0.40000000000000002, "a0.kix": 0.40000000000000002, "a0.ending_iteration": 999, "return_val2": null, "a0.kdx": 15, "a0.kdy": 15, "a0.kdz": 30}, {"ith_runtime": 24.32086205482483, "setpoint": [1, 1, 2], "a0.kpx": 20, "a0.kpy": 20, "a0.kpz": 20, "a0.kiz": 35, "a0.kiy": 0.40000000000000002, "a0.kix": 0.40000000000000002, "a0.ending_iteration": 999, "return_val2": null, "a0.kdx": 15, "a0.kdy": 15, "a0.kdz": 30}, {"ith_runtime": 21.179394006729126, "setpoint": [1, 1, 2], "a0.kpx": 20, "a0.kpy": 20, "a0.kpz": 20, "a0.kiz": 40, "a0.kiy": 0.40000000000000002, "a0.kix": 0.40000000000000002, "a0.ending_iteration": 999, "return_val2": null, "a0.kdx": 15, "a0.kdy": 15, "a0.kdz": 30}]